MANIFEST.in
setup.py
TriWords/TriWords.py
TriWords/__init__.py
TriWords.egg-info/PKG-INFO
TriWords.egg-info/SOURCES.txt
TriWords.egg-info/dependency_links.txt
TriWords.egg-info/top_level.txt
XMLcollection1/PMC6988269.xml
XMLcollection1/PMC6988271.xml
XMLcollection1/PMC6988272.xml
XMLcollection1/PMC6995816.xml
XMLcollection1/PMC7001239.xml
XMLcollection1/PMC7001240.xml
XMLcollection1/PMC7003341.xml
XMLcollection1/PMC7004396.xml
XMLcollection1/PMC7008072.xml
XMLcollection1/PMC7008073.xml
XMLcollection1/PMC7011107.xml
XMLcollection1/PMC7014668.xml
XMLcollection1/PMC7014669.xml
XMLcollection1/PMC7014672.xml
XMLcollection1/PMC7017878.xml
XMLcollection1/PMC7017962.xml
XMLcollection1/PMC7019868.xml
XMLcollection1/PMC7025910.xml
XMLcollection1/PMC7026896.xml
XMLcollection1/PMC7029158.xml
XMLcollection1/PMC7029402.xml
XMLcollection1/PMC7029448.xml
XMLcollection1/PMC7029449.xml
XMLcollection1/PMC7029450.xml
XMLcollection1/PMC7029452.xml
XMLcollection1/PMC7029610.xml
XMLcollection1/PMC7029759.xml
XMLcollection1/PMC7031769.xml
XMLcollection1/PMC7031771.xml
XMLcollection1/PMC7033263.xml
XMLcollection1/PMC7033275.xml
XMLcollection1/PMC7033348.xml
XMLcollection1/PMC7033698.xml
XMLcollection1/PMC7033706.xml
XMLcollection1/PMC7033720.xml
XMLcollection1/PMC7035340.xml
XMLcollection1/PMC7081176.xml
XMLcollection1/PMC7082074.xml
XMLcollection1/PMC7084952.xml
XMLcollection1/PMC7319648.xml
XMLcollection1/PMC7319773.xml
XMLcollection1/PMC7320676.xml
XMLcollection1/PMC7321036.xml
XMLcollection1/PMC7323033.xml
XMLcollection1/PMC7323037.xml
XMLcollection1/PMC7323060.xml
XMLcollection1/PMC7323234.xml
XMLcollection1/PMC7323243.xml
XMLcollection1/PMC7323291.xml
XMLcollection1/PMC7323302.xml
XMLcollection1/PMC7323390.xml
XMLcollection1/PMC7323403.xml
XMLcollection1/PMC7323437.xml
XMLcollection1/PMC7323606.xml
XMLcollection1/PMC7324709.xml
XMLcollection1/PMC7324760.xml
XMLcollection1/PMC7324763.xml
XMLcollection1/PMC7325519.xml
XMLcollection1/PMC7326040.xml
XMLcollection1/PMC7328585.xml
XMLcollection1/desktop.ini