Metadata-Version: 2.1
Name: TriWords
Version: 1.0.0
Summary: Get the main word in the paper
Home-page: https://github.com/ReddishXia/TheMainword
Author: 79988
Author-email: 77957147@qq.com
License: MIT
Platform: UNKNOWN
